Metadata-Version: 1.1
Name: xbox360controller
Version: 1.0.6
Summary: A pythonic Xbox360 controller API built on top of the xpad Linux kernel driver.
Home-page: https://github.com/linusg/xbox360controller
Author: Linus Groh
Author-email: mail@linusgroh.de
License: MIT
Download-URL: https://pypi.org/project/xbox360controller/
Keywords: xbox,xbox360,controller,gamepad,game,raspberry pi,event,led,rumble
Platform: UNKNOWN
Classifier: Development Status :: 3 - Alpha
Classifier: Intended Audience :: Developers
Classifier: License :: OSI Approved :: MIT License
Classifier: Operating System :: POSIX :: Linux
Classifier: Programming Language :: Python
Classifier: Programming Language :: Python :: 3
Classifier: Programming Language :: Python :: 3.4
Classifier: Programming Language :: Python :: 3.5
Classifier: Programming Language :: Python :: 3.6
Classifier: Programming Language :: Python :: 3.7
Classifier: Programming Language :: Python :: 3 :: Only
Classifier: Topic :: Games/Entertainment
Classifier: Topic :: Software Development :: Libraries
Classifier: Topic :: Software Development :: Libraries :: Python Modules
Classifier: Topic :: System
Classifier: Topic :: System :: Hardware
Classifier: Topic :: System :: Hardware :: Hardware Drivers
Classifier: Topic :: Utilities
